annotald/annotald-win.py
annotald/settings.py
annotald/treedrawing.py
annotald/util_test.py
annotald/util.py
annotald/settings.js
annotald/__init__.py
annotald/data/css/jquery.contextMenu.css
annotald/data/css/treedrawing.css
annotald/data/html/index.mako
annotald/data/html/logs.mako
annotald/data/images/cut.png
annotald/data/images/door.png
annotald/data/images/page_white_copy.png
annotald/data/images/page_white_delete.png
annotald/data/images/page_white_edit.png
annotald/data/images/page_white_paste.png
annotald/data/scripts/jquery-debug.js
annotald/data/scripts/jquery.contextmenu.js
annotald/data/scripts/jquery.js
annotald/data/scripts/jquery.mousewheel.min.js
annotald/data/scripts/test.js
annotald/data/scripts/underscore-min.js
annotald/data/scripts/treedrawing.contextMenu.js
annotald/data/scripts/treedrawing.js
annotald/data/scripts/treedrawing.utils.js
annotald-1.3.8.data/scripts/annotald
annotald-1.3.8.data/scripts/annotald-aux
annotald-1.3.8.dist-info/top_level.txt
annotald-1.3.8.dist-info/METADATA
annotald-1.3.8.dist-info/DESCRIPTION.rst
annotald-1.3.8.dist-info/pydist.json
annotald-1.3.8.dist-info/WHEEL
annotald-1.3.8.dist-info/RECORD
