Metadata-Version: 2.0
Name: annotald
Version: 1.3.8
Summary: A GUI for treebank annotation
Home-page: http://annotald.github.com/
Author: Aaron Ecay, Anton Karl Ingason and Jana Beck
Author-email: aaronecay@gmail.com
License: GPLv3+
Platform: UNKNOWN
Classifier: Development Status :: 4 - Beta
Classifier: Intended Audience :: Education
Classifier: License :: OSI Approved :: GNU General Public License v3 or later (GPLv3+)
Classifier: Topic :: Scientific/Engineering
Provides: annotald
Requires-Dist: mako
Requires-Dist: cherrypy
Requires-Dist: argparse
Requires-Dist: nltk (==2.0.5)
